{
  "last_updated": "2026-02-25T13:07:00Z",
  "stocks": [
    {"symbol": "SNDK", "sctr": 99.9},
    {"symbol": "LITE", "sctr": 99.7},
    {"symbol": "CIEN", "sctr": 99.6},
    {"symbol": "AG", "sctr": 99.5},
    {"symbol": "MU", "sctr": 99.4},
    {"symbol": "BE", "sctr": 99.3},
    {"symbol": "WDC", "sctr": 99.2},
    {"symbol": "TER", "sctr": 99.1},
    {"symbol": "SATS", "sctr": 99.0},
    {"symbol": "COHR", "sctr": 98.9},
    {"symbol": "GLW", "sctr": 98.7},
    {"symbol": "RVMD", "sctr": 98.6},
    {"symbol": "HL", "sctr": 98.5},
    {"symbol": "ASX", "sctr": 98.4},
    {"symbol": "TTMI", "sctr": 98.3},
    {"symbol": "AU", "sctr": 98.2},
    {"symbol": "ROIV", "sctr": 98.1},
    {"symbol": "ATI", "sctr": 98.0},
    {"symbol": "MKSI", "sctr": 97.9},
    {"symbol": "LRCX", "sctr": 97.7}
  ]
}
